arcGisFeatureCache/__init__.py
arcGisFeatureCache/arcGisScraper.py
arcGisFeatureCache/featureLayer.py
arcGisFeatureCache/featureService.py
arcGisFeatureCache/py.typed
arcGisFeatureCache/models/__init__.py
arcGisFeatureCache/models/attributes.py
arcGisFeatureCache/models/feature.py
arcGisFeatureCache/models/geometry.py
arcGisFeatureCache/utils/__init__.py
arcGisFeatureCache/utils/helpers.py
arcGisFeatureCache/utils/immutableList.py
arcGisFeatureCache/utils/log.py
arcgisfeaturecache-0.1.0rc1.dev2.dist-info/METADATA
arcgisfeaturecache-0.1.0rc1.dev2.dist-info/WHEEL
arcgisfeaturecache-0.1.0rc1.dev2.dist-info/licenses/LICENSE.md
arcgisfeaturecache-0.1.0rc1.dev2.dist-info/RECORD
