Metadata-Version: 2.1
Name: arcGisFeatureCache
Version: 0.1.0rc1.dev2
Summary: ...
Project-URL: Documentation, https://Hazedd.github.io/ArcGisFeatureCache/
Project-URL: Source, https://github.com/ArcGisFeatureCache
Author-email: ArcGisFeatureCache <Hazedd@no-replay.github.com>
License-File: LICENSE.md
Classifier: Intended Audience :: Developers
Classifier: Programming Language :: Python :: 3 :: Only
Classifier: Programming Language :: Python :: 3.12
Requires-Python: >=3.10
Requires-Dist: httpx
Requires-Dist: loguru
Requires-Dist: numpy
Requires-Dist: shapely
